dict_picker-0.1.5.dist-info/METADATA
dict_picker-0.1.5.dist-info/WHEEL
dict_picker-0.1.5.dist-info/license_files/LICENSE
dict_picker/__init__.py
dict_picker/dict_picker.cpython-39-powerpc64le-linux-gnu.so
dict_picker-0.1.5.dist-info/RECORD
