Metadata-Version: 2.1
Name: dict-picker
Version: 0.1.5
Classifier: Programming Language :: Rust
Classifier: Programming Language :: Python :: Implementation :: CPython
Classifier: Programming Language :: Python :: Implementation :: PyPy
License-File: LICENSE
Summary: Fast key search in python
Requires-Python: >=3.7
Project-URL: Homepage, https://github.com/sarvensis/dict-picker
